his
testHis
