Metadata-Version: 1.1
Name: app-his-migrator
Version: 1.0.3
Summary: Este aplicativo se utiliza para migrar la informacion de atenciones al HIS MINSA
Home-page: UNKNOWN
Author: ODT
Author-email: aajrf1992@gmail.com
License: BSD
Platform: UNKNOWN
Classifier: Development Status :: 3 - Alpha
Classifier: License :: OSI Approved :: BSD License
Classifier: Programming Language :: Python :: 2.7
Classifier: Topic :: Utilities
